hatch_build/__init__.py
hatch_build/cli.py
hatch_build/tests/test_all.py
hatch_build/tests/test_cli.py
hatch_build/tests/test_cli_model.py
hatch_build-0.5.0.dist-info/METADATA
hatch_build-0.5.0.dist-info/WHEEL
hatch_build-0.5.0.dist-info/entry_points.txt
hatch_build-0.5.0.dist-info/licenses/LICENSE
hatch_build-0.5.0.dist-info/RECORD
